assert_no_inline_directives/__init__.py
assert_no_inline_directives/__main__.py
assert_no_inline_directives/cli.py
assert_no_inline_directives/py.typed
assert_no_inline_directives/scanner.py
assert_no_inline_directives-20260104142245.dist-info/licenses/LICENSE.txt
assert_no_inline_directives-20260104142245.dist-info/METADATA
assert_no_inline_directives-20260104142245.dist-info/WHEEL
assert_no_inline_directives-20260104142245.dist-info/entry_points.txt
assert_no_inline_directives-20260104142245.dist-info/top_level.txt
assert_no_inline_directives-20260104142245.dist-info/RECORD
