Metadata-Version: 2.4
Name: assert-no-inline-directives
Version: 20260104142245
Summary: CLI tool to assert that files contain no inline directives
Author-email: 10U Labs <dev@10ulabs.com>
License-Expression: Apache-2.0
Project-URL: Homepage, https://github.com/10U-Labs-LLC/assert-no-inline-directives
Project-URL: Issues, https://github.com/10U-Labs-LLC/assert-no-inline-directives/issues
Project-URL: Repository, https://github.com/10U-Labs-LLC/assert-no-inline-directives
Classifier: Development Status :: 4 - Beta
Classifier: Environment :: Console
Classifier: Intended Audience :: Developers
Classifier: Programming Language :: Python :: 3
Classifier: Programming Language :: Python :: 3.10
Classifier: Programming Language :: Python :: 3.11
Classifier: Programming Language :: Python :: 3.12
Classifier: Programming Language :: Python :: 3.13
Classifier: Topic :: Software Development :: Quality Assurance
Requires-Python: >=3.10
License-File: LICENSE.txt
Dynamic: license-file
